galaxy_ie_helpers/__init__.py
galaxy_ie_helpers-0.2.7.data/scripts/get
galaxy_ie_helpers-0.2.7.data/scripts/get_user_history
galaxy_ie_helpers-0.2.7.data/scripts/put
galaxy_ie_helpers-0.2.7.dist-info/LICENSE
galaxy_ie_helpers-0.2.7.dist-info/METADATA
galaxy_ie_helpers-0.2.7.dist-info/WHEEL
galaxy_ie_helpers-0.2.7.dist-info/top_level.txt
galaxy_ie_helpers-0.2.7.dist-info/RECORD
