Metadata-Version: 2.1
Name: galaxy-ie-helpers
Version: 0.2.7
Summary: Helper scripts to work with Galaxy's Interactive Environments
Home-page: https://github.com/bgruening/galaxy_ie_helpers
Author: Bjoern A. Gruening; Helena Rasche
Author-email: bjoern.gruening@gmail.com
License: LICENSE
Keywords: Galaxy,Interactive Environments
Platform: UNKNOWN
Classifier: Development Status :: 5 - Production/Stable
Classifier: Intended Audience :: Developers
Classifier: Environment :: Console
Classifier: License :: OSI Approved :: MIT License
Classifier: Operating System :: POSIX
Classifier: Topic :: Software Development
Classifier: Topic :: Software Development :: Code Generators
Classifier: Natural Language :: English
Classifier: Programming Language :: Python :: 2
Classifier: Programming Language :: Python :: 2.7
License-File: LICENSE
Requires-Dist: bioblend
